OffSecItaXer173/__init__.py
OffSecItaXer173/corsi.py
OffSecItaXer173/utils.py
OffSecItaXer173-0.1.2.dist-info/METADATA
OffSecItaXer173-0.1.2.dist-info/WHEEL
OffSecItaXer173-0.1.2.dist-info/top_level.txt
OffSecItaXer173-0.1.2.dist-info/RECORD
